{
  "papi_version":"6.0.0.17",
  "cpu_info":"AMD EPYC 7742 64-Core Processor",
  "max_cpu_rate_mhz":"2250",
  "min_cpu_rate_mhz":"1500",
  "event_definitions":{
    "PAPI_FP_OPS":{
      "component":"perf_event",
      "type":"delta"
    },
    "PERF_COUNT_HW_CACHE_L1D:MISS":{
      "component":"perf_event",
      "type":"delta"
    }
  },
  "threads":{
    "0":{
      "regions":{
        "0":{
          "name":"initialize",
          "parent_region_id":"-1",
          "cycles":"130793",
          "real_time_nsec":"54224",
          "PAPI_FP_OPS":"3200",
          "PERF_COUNT_HW_CACHE_L1D:MISS":"350"
        },
        "1":{
          "name":"ijk",
          "parent_region_id":"-1",
          "cycles":"193072",
          "real_time_nsec":"85705",
          "PAPI_FP_OPS":"128000",
          "PERF_COUNT_HW_CACHE_L1D:MISS":"239"
        },
        "2":{
          "name":"ikj",
          "parent_region_id":"-1",
          "cycles":"126360",
          "real_time_nsec":"56107",
          "PAPI_FP_OPS":"128000",
          "PERF_COUNT_HW_CACHE_L1D:MISS":"152"
        },
        "3":{
          "name":"jik",
          "parent_region_id":"-1",
          "cycles":"197888",
          "real_time_nsec":"87968",
          "PAPI_FP_OPS":"128000",
          "PERF_COUNT_HW_CACHE_L1D:MISS":"111"
        },
        "4":{
          "name":"jki",
          "parent_region_id":"-1",
          "cycles":"129150",
          "real_time_nsec":"57390",
          "PAPI_FP_OPS":"128000",
          "PERF_COUNT_HW_CACHE_L1D:MISS":"107"
        },
        "5":{
          "name":"kij",
          "parent_region_id":"-1",
          "cycles":"207383",
          "real_time_nsec":"92247",
          "PAPI_FP_OPS":"128000",
          "PERF_COUNT_HW_CACHE_L1D:MISS":"104"
        },
        "6":{
          "name":"kji",
          "parent_region_id":"-1",
          "cycles":"179235",
          "real_time_nsec":"79713",
          "PAPI_FP_OPS":"128000",
          "PERF_COUNT_HW_CACHE_L1D:MISS":"73"
        }
      }
    }
  }
}
