{
  "papi_version":"6.0.0.17",
  "cpu_info":"AMD EPYC 7742 64-Core Processor",
  "max_cpu_rate_mhz":"2250",
  "min_cpu_rate_mhz":"1500",
  "event_definitions":{
    "PAPI_FP_OPS":{
      "component":"perf_event",
      "type":"delta"
    },
    "PERF_COUNT_HW_CACHE_L1D:MISS":{
      "component":"perf_event",
      "type":"delta"
    }
  },
  "threads":{
    "0":{
      "regions":{
        "0":{
          "name":"initialize",
          "parent_region_id":"-1",
          "cycles":"8057070",
          "real_time_nsec":"3584902",
          "PAPI_FP_OPS":"320000",
          "PERF_COUNT_HW_CACHE_L1D:MISS":"20369"
        },
        "1":{
          "name":"ijk",
          "parent_region_id":"-1",
          "cycles":"137307127",
          "real_time_nsec":"61143486",
          "PAPI_FP_OPS":"128000000",
          "PERF_COUNT_HW_CACHE_L1D:MISS":"27461156"
        },
        "2":{
          "name":"ikj",
          "parent_region_id":"-1",
          "cycles":"102415253",
          "real_time_nsec":"45605120",
          "PAPI_FP_OPS":"128000000",
          "PERF_COUNT_HW_CACHE_L1D:MISS":"60471124"
        },
        "3":{
          "name":"jik",
          "parent_region_id":"-1",
          "cycles":"207868613",
          "real_time_nsec":"92563575",
          "PAPI_FP_OPS":"128000000",
          "PERF_COUNT_HW_CACHE_L1D:MISS":"64989828"
        },
        "4":{
          "name":"jki",
          "parent_region_id":"-1",
          "cycles":"69168105",
          "real_time_nsec":"30800511",
          "PAPI_FP_OPS":"128000000",
          "PERF_COUNT_HW_CACHE_L1D:MISS":"4040810"
        },
        "5":{
          "name":"kij",
          "parent_region_id":"-1",
          "cycles":"212514660",
          "real_time_nsec":"94633612",
          "PAPI_FP_OPS":"128000000",
          "PERF_COUNT_HW_CACHE_L1D:MISS":"122388927"
        },
        "6":{
          "name":"kji",
          "parent_region_id":"-1",
          "cycles":"98771017",
          "real_time_nsec":"43982630",
          "PAPI_FP_OPS":"128000000",
          "PERF_COUNT_HW_CACHE_L1D:MISS":"4200386"
        }
      }
    }
  }
}
