{
  "papi_version":"6.0.0.17",
  "cpu_info":"AMD EPYC 7742 64-Core Processor",
  "max_cpu_rate_mhz":"2250",
  "min_cpu_rate_mhz":"1500",
  "event_definitions":{
    "PAPI_FP_OPS":{
      "component":"perf_event",
      "type":"delta"
    },
    "PERF_COUNT_HW_CACHE_L1D:MISS":{
      "component":"perf_event",
      "type":"delta"
    }
  },
  "threads":{
    "0":{
      "regions":{
        "0":{
          "name":"initialize",
          "parent_region_id":"-1",
          "cycles":"8934682",
          "real_time_nsec":"3976973",
          "PAPI_FP_OPS":"320000",
          "PERF_COUNT_HW_CACHE_L1D:MISS":"22512"
        },
        "1":{
          "name":"ijk",
          "parent_region_id":"-1",
          "cycles":"156286373",
          "real_time_nsec":"69594686",
          "PAPI_FP_OPS":"128000000",
          "PERF_COUNT_HW_CACHE_L1D:MISS":"34944439"
        },
        "2":{
          "name":"ikj",
          "parent_region_id":"-1",
          "cycles":"111412890",
          "real_time_nsec":"49611431",
          "PAPI_FP_OPS":"128000000",
          "PERF_COUNT_HW_CACHE_L1D:MISS":"60668279"
        },
        "3":{
          "name":"jik",
          "parent_region_id":"-1",
          "cycles":"165900713",
          "real_time_nsec":"73875312",
          "PAPI_FP_OPS":"128000000",
          "PERF_COUNT_HW_CACHE_L1D:MISS":"59357825"
        },
        "4":{
          "name":"jki",
          "parent_region_id":"-1",
          "cycles":"77684107",
          "real_time_nsec":"34592160",
          "PAPI_FP_OPS":"128000000",
          "PERF_COUNT_HW_CACHE_L1D:MISS":"4033929"
        },
        "5":{
          "name":"kij",
          "parent_region_id":"-1",
          "cycles":"202164075",
          "real_time_nsec":"90023606",
          "PAPI_FP_OPS":"128000000",
          "PERF_COUNT_HW_CACHE_L1D:MISS":"122942247"
        },
        "6":{
          "name":"kji",
          "parent_region_id":"-1",
          "cycles":"62070210",
          "real_time_nsec":"27639572",
          "PAPI_FP_OPS":"128000000",
          "PERF_COUNT_HW_CACHE_L1D:MISS":"4213138"
        }
      }
    }
  }
}
