{
  "papi_version":"6.0.0.17",
  "cpu_info":"AMD EPYC 7742 64-Core Processor",
  "max_cpu_rate_mhz":"2250",
  "min_cpu_rate_mhz":"1500",
  "event_definitions":{
    "PAPI_FP_OPS":{
      "component":"perf_event",
      "type":"delta"
    },
    "PERF_COUNT_HW_CACHE_L1D:MISS":{
      "component":"perf_event",
      "type":"delta"
    }
  },
  "threads":{
    "0":{
      "regions":{
        "0":{
          "name":"initialize",
          "parent_region_id":"-1",
          "cycles":"9319072",
          "real_time_nsec":"4148111",
          "PAPI_FP_OPS":"320000",
          "PERF_COUNT_HW_CACHE_L1D:MISS":"21125"
        },
        "1":{
          "name":"ijk",
          "parent_region_id":"-1",
          "cycles":"160579282",
          "real_time_nsec":"71505929",
          "PAPI_FP_OPS":"128000000",
          "PERF_COUNT_HW_CACHE_L1D:MISS":"42416921"
        },
        "2":{
          "name":"ikj",
          "parent_region_id":"-1",
          "cycles":"100763640",
          "real_time_nsec":"44869771",
          "PAPI_FP_OPS":"128000000",
          "PERF_COUNT_HW_CACHE_L1D:MISS":"60483078"
        },
        "3":{
          "name":"jik",
          "parent_region_id":"-1",
          "cycles":"164790990",
          "real_time_nsec":"73381655",
          "PAPI_FP_OPS":"128000000",
          "PERF_COUNT_HW_CACHE_L1D:MISS":"61486964"
        },
        "4":{
          "name":"jki",
          "parent_region_id":"-1",
          "cycles":"64667272",
          "real_time_nsec":"28796409",
          "PAPI_FP_OPS":"128000000",
          "PERF_COUNT_HW_CACHE_L1D:MISS":"4034492"
        },
        "5":{
          "name":"kij",
          "parent_region_id":"-1",
          "cycles":"181943100",
          "real_time_nsec":"81019547",
          "PAPI_FP_OPS":"128000000",
          "PERF_COUNT_HW_CACHE_L1D:MISS":"124538889"
        },
        "6":{
          "name":"kji",
          "parent_region_id":"-1",
          "cycles":"230475510",
          "real_time_nsec":"102630712",
          "PAPI_FP_OPS":"128000000",
          "PERF_COUNT_HW_CACHE_L1D:MISS":"4173913"
        }
      }
    }
  }
}
