{
  "papi_version":"6.0.0.17",
  "cpu_info":"AMD EPYC 7742 64-Core Processor",
  "max_cpu_rate_mhz":"2250",
  "min_cpu_rate_mhz":"1500",
  "event_definitions":{
    "PAPI_FP_OPS":{
      "component":"perf_event",
      "type":"delta"
    },
    "PERF_COUNT_HW_CACHE_L1D:MISS":{
      "component":"perf_event",
      "type":"delta"
    }
  },
  "threads":{
    "0":{
      "regions":{
        "0":{
          "name":"initialize",
          "parent_region_id":"-1",
          "cycles":"6467512",
          "real_time_nsec":"2876033",
          "PAPI_FP_OPS":"320000",
          "PERF_COUNT_HW_CACHE_L1D:MISS":"20701"
        },
        "1":{
          "name":"ijk",
          "parent_region_id":"-1",
          "cycles":"134744422",
          "real_time_nsec":"60002188",
          "PAPI_FP_OPS":"128000000",
          "PERF_COUNT_HW_CACHE_L1D:MISS":"26467091"
        },
        "2":{
          "name":"ikj",
          "parent_region_id":"-1",
          "cycles":"99992903",
          "real_time_nsec":"44526553",
          "PAPI_FP_OPS":"128000000",
          "PERF_COUNT_HW_CACHE_L1D:MISS":"60378585"
        },
        "3":{
          "name":"jik",
          "parent_region_id":"-1",
          "cycles":"149559300",
          "real_time_nsec":"66598553",
          "PAPI_FP_OPS":"128000000",
          "PERF_COUNT_HW_CACHE_L1D:MISS":"64912759"
        },
        "4":{
          "name":"jki",
          "parent_region_id":"-1",
          "cycles":"75157695",
          "real_time_nsec":"33467704",
          "PAPI_FP_OPS":"128000000",
          "PERF_COUNT_HW_CACHE_L1D:MISS":"4032544"
        },
        "5":{
          "name":"kij",
          "parent_region_id":"-1",
          "cycles":"206159378",
          "real_time_nsec":"91803017",
          "PAPI_FP_OPS":"128000000",
          "PERF_COUNT_HW_CACHE_L1D:MISS":"120587676"
        },
        "6":{
          "name":"kji",
          "parent_region_id":"-1",
          "cycles":"72620617",
          "real_time_nsec":"32338319",
          "PAPI_FP_OPS":"128000000",
          "PERF_COUNT_HW_CACHE_L1D:MISS":"4209375"
        }
      }
    }
  }
}
