{
  "papi_version":"6.0.0.17",
  "cpu_info":"AMD EPYC 7742 64-Core Processor",
  "max_cpu_rate_mhz":"2250",
  "min_cpu_rate_mhz":"1500",
  "event_definitions":{
    "PAPI_FP_OPS":{
      "component":"perf_event",
      "type":"delta"
    },
    "PERF_COUNT_HW_CACHE_L1D:MISS":{
      "component":"perf_event",
      "type":"delta"
    }
  },
  "threads":{
    "0":{
      "regions":{
        "0":{
          "name":"initialize",
          "parent_region_id":"-1",
          "cycles":"129893",
          "real_time_nsec":"55567",
          "PAPI_FP_OPS":"5000",
          "PERF_COUNT_HW_CACHE_L1D:MISS":"665"
        },
        "1":{
          "name":"ijk",
          "parent_region_id":"-1",
          "cycles":"307913",
          "real_time_nsec":"137073",
          "PAPI_FP_OPS":"250000",
          "PERF_COUNT_HW_CACHE_L1D:MISS":"918"
        },
        "2":{
          "name":"ikj",
          "parent_region_id":"-1",
          "cycles":"146970",
          "real_time_nsec":"65395",
          "PAPI_FP_OPS":"250000",
          "PERF_COUNT_HW_CACHE_L1D:MISS":"867"
        },
        "3":{
          "name":"jik",
          "parent_region_id":"-1",
          "cycles":"230872",
          "real_time_nsec":"102767",
          "PAPI_FP_OPS":"250000",
          "PERF_COUNT_HW_CACHE_L1D:MISS":"5981"
        },
        "4":{
          "name":"jki",
          "parent_region_id":"-1",
          "cycles":"152280",
          "real_time_nsec":"67729",
          "PAPI_FP_OPS":"250000",
          "PERF_COUNT_HW_CACHE_L1D:MISS":"5703"
        },
        "5":{
          "name":"kij",
          "parent_region_id":"-1",
          "cycles":"253282",
          "real_time_nsec":"112736",
          "PAPI_FP_OPS":"250000",
          "PERF_COUNT_HW_CACHE_L1D:MISS":"1282"
        },
        "6":{
          "name":"kji",
          "parent_region_id":"-1",
          "cycles":"195682",
          "real_time_nsec":"87076",
          "PAPI_FP_OPS":"250000",
          "PERF_COUNT_HW_CACHE_L1D:MISS":"1799"
        }
      }
    }
  }
}
