{
  "papi_version":"6.0.0.17",
  "cpu_info":"AMD EPYC 7742 64-Core Processor",
  "max_cpu_rate_mhz":"2250",
  "min_cpu_rate_mhz":"1500",
  "event_definitions":{
    "PAPI_FP_OPS":{
      "component":"perf_event",
      "type":"delta"
    },
    "PERF_COUNT_HW_CACHE_L1D:MISS":{
      "component":"perf_event",
      "type":"delta"
    }
  },
  "threads":{
    "0":{
      "regions":{
        "0":{
          "name":"initialize",
          "parent_region_id":"-1",
          "cycles":"19509750",
          "real_time_nsec":"8684056",
          "PAPI_FP_OPS":"720000",
          "PERF_COUNT_HW_CACHE_L1D:MISS":"47387"
        },
        "1":{
          "name":"ijk",
          "parent_region_id":"-1",
          "cycles":"605413620",
          "real_time_nsec":"269590628",
          "PAPI_FP_OPS":"432000000",
          "PERF_COUNT_HW_CACHE_L1D:MISS":"211501497"
        },
        "2":{
          "name":"ikj",
          "parent_region_id":"-1",
          "cycles":"401000355",
          "real_time_nsec":"178564019",
          "PAPI_FP_OPS":"432000000",
          "PERF_COUNT_HW_CACHE_L1D:MISS":"217577672"
        },
        "3":{
          "name":"jik",
          "parent_region_id":"-1",
          "cycles":"534898553",
          "real_time_nsec":"238189835",
          "PAPI_FP_OPS":"432000000",
          "PERF_COUNT_HW_CACHE_L1D:MISS":"222629219"
        },
        "4":{
          "name":"jki",
          "parent_region_id":"-1",
          "cycles":"196220835",
          "real_time_nsec":"87377373",
          "PAPI_FP_OPS":"432000000",
          "PERF_COUNT_HW_CACHE_L1D:MISS":"13702328"
        },
        "5":{
          "name":"kij",
          "parent_region_id":"-1",
          "cycles":"779102213",
          "real_time_nsec":"346933476",
          "PAPI_FP_OPS":"432000000",
          "PERF_COUNT_HW_CACHE_L1D:MISS":"432401803"
        },
        "6":{
          "name":"kji",
          "parent_region_id":"-1",
          "cycles":"212906227",
          "real_time_nsec":"94806956",
          "PAPI_FP_OPS":"432000000",
          "PERF_COUNT_HW_CACHE_L1D:MISS":"14093970"
        }
      }
    }
  }
}
