{
  "papi_version":"6.0.0.17",
  "cpu_info":"AMD EPYC 7742 64-Core Processor",
  "max_cpu_rate_mhz":"2250",
  "min_cpu_rate_mhz":"1500",
  "event_definitions":{
    "PAPI_FP_OPS":{
      "component":"perf_event",
      "type":"delta"
    },
    "PERF_COUNT_HW_CACHE_L1D:MISS":{
      "component":"perf_event",
      "type":"delta"
    }
  },
  "threads":{
    "0":{
      "regions":{
        "0":{
          "name":"initialize",
          "parent_region_id":"-1",
          "cycles":"20926620",
          "real_time_nsec":"9315957",
          "PAPI_FP_OPS":"720000",
          "PERF_COUNT_HW_CACHE_L1D:MISS":"49558"
        },
        "1":{
          "name":"ijk",
          "parent_region_id":"-1",
          "cycles":"541613070",
          "real_time_nsec":"241180148",
          "PAPI_FP_OPS":"432000000",
          "PERF_COUNT_HW_CACHE_L1D:MISS":"207038491"
        },
        "2":{
          "name":"ikj",
          "parent_region_id":"-1",
          "cycles":"396829530",
          "real_time_nsec":"176707099",
          "PAPI_FP_OPS":"432000000",
          "PERF_COUNT_HW_CACHE_L1D:MISS":"217722401"
        },
        "3":{
          "name":"jik",
          "parent_region_id":"-1",
          "cycles":"528247530",
          "real_time_nsec":"235228229",
          "PAPI_FP_OPS":"432000000",
          "PERF_COUNT_HW_CACHE_L1D:MISS":"222722869"
        },
        "4":{
          "name":"jki",
          "parent_region_id":"-1",
          "cycles":"193695323",
          "real_time_nsec":"86252537",
          "PAPI_FP_OPS":"432000000",
          "PERF_COUNT_HW_CACHE_L1D:MISS":"13704448"
        },
        "5":{
          "name":"kij",
          "parent_region_id":"-1",
          "cycles":"771656737",
          "real_time_nsec":"343617941",
          "PAPI_FP_OPS":"432000000",
          "PERF_COUNT_HW_CACHE_L1D:MISS":"432369139"
        },
        "6":{
          "name":"kji",
          "parent_region_id":"-1",
          "cycles":"225342158",
          "real_time_nsec":"100344580",
          "PAPI_FP_OPS":"432000000",
          "PERF_COUNT_HW_CACHE_L1D:MISS":"14055967"
        }
      }
    }
  }
}
