{
  "papi_version":"6.0.0.17",
  "cpu_info":"AMD EPYC 7742 64-Core Processor",
  "max_cpu_rate_mhz":"2250",
  "min_cpu_rate_mhz":"1500",
  "event_definitions":{
    "PAPI_FP_OPS":{
      "component":"perf_event",
      "type":"delta"
    },
    "PERF_COUNT_HW_CACHE_L1D:MISS":{
      "component":"perf_event",
      "type":"delta"
    }
  },
  "threads":{
    "0":{
      "regions":{
        "0":{
          "name":"initialize",
          "parent_region_id":"-1",
          "cycles":"6157620",
          "real_time_nsec":"2740754",
          "PAPI_FP_OPS":"320000",
          "PERF_COUNT_HW_CACHE_L1D:MISS":"20528"
        },
        "1":{
          "name":"ijk",
          "parent_region_id":"-1",
          "cycles":"156797550",
          "real_time_nsec":"69822573",
          "PAPI_FP_OPS":"128000000",
          "PERF_COUNT_HW_CACHE_L1D:MISS":"48586813"
        },
        "2":{
          "name":"ikj",
          "parent_region_id":"-1",
          "cycles":"78084067",
          "real_time_nsec":"34770146",
          "PAPI_FP_OPS":"128000000",
          "PERF_COUNT_HW_CACHE_L1D:MISS":"4036399"
        },
        "3":{
          "name":"jik",
          "parent_region_id":"-1",
          "cycles":"221549130",
          "real_time_nsec":"98656310",
          "PAPI_FP_OPS":"128000000",
          "PERF_COUNT_HW_CACHE_L1D:MISS":"38707765"
        },
        "4":{
          "name":"jki",
          "parent_region_id":"-1",
          "cycles":"117538110",
          "real_time_nsec":"52339769",
          "PAPI_FP_OPS":"128000000",
          "PERF_COUNT_HW_CACHE_L1D:MISS":"62064806"
        },
        "5":{
          "name":"kij",
          "parent_region_id":"-1",
          "cycles":"134317598",
          "real_time_nsec":"59811192",
          "PAPI_FP_OPS":"128000000",
          "PERF_COUNT_HW_CACHE_L1D:MISS":"4192834"
        },
        "6":{
          "name":"kji",
          "parent_region_id":"-1",
          "cycles":"239837962",
          "real_time_nsec":"106799862",
          "PAPI_FP_OPS":"128000000",
          "PERF_COUNT_HW_CACHE_L1D:MISS":"126663322"
        }
      }
    }
  }
}
