{
  "papi_version":"6.0.0.17",
  "cpu_info":"AMD EPYC 7742 64-Core Processor",
  "max_cpu_rate_mhz":"2250",
  "min_cpu_rate_mhz":"1500",
  "event_definitions":{
    "PAPI_FP_OPS":{
      "component":"perf_event",
      "type":"delta"
    },
    "PERF_COUNT_HW_CACHE_L1D:MISS":{
      "component":"perf_event",
      "type":"delta"
    }
  },
  "threads":{
    "0":{
      "regions":{
        "0":{
          "name":"initialize",
          "parent_region_id":"-1",
          "cycles":"13808475",
          "real_time_nsec":"6145280",
          "PAPI_FP_OPS":"180000",
          "PERF_COUNT_HW_CACHE_L1D:MISS":"11647"
        },
        "1":{
          "name":"ijk",
          "parent_region_id":"-1",
          "cycles":"52483455",
          "real_time_nsec":"23370950",
          "PAPI_FP_OPS":"54000000",
          "PERF_COUNT_HW_CACHE_L1D:MISS":"2302662"
        },
        "2":{
          "name":"ikj",
          "parent_region_id":"-1",
          "cycles":"38384370",
          "real_time_nsec":"17093056",
          "PAPI_FP_OPS":"54000000",
          "PERF_COUNT_HW_CACHE_L1D:MISS":"23980962"
        },
        "3":{
          "name":"jik",
          "parent_region_id":"-1",
          "cycles":"61655107",
          "real_time_nsec":"27455269",
          "PAPI_FP_OPS":"54000000",
          "PERF_COUNT_HW_CACHE_L1D:MISS":"5735461"
        },
        "4":{
          "name":"jki",
          "parent_region_id":"-1",
          "cycles":"24019672",
          "real_time_nsec":"10695652",
          "PAPI_FP_OPS":"54000000",
          "PERF_COUNT_HW_CACHE_L1D:MISS":"1703050"
        },
        "5":{
          "name":"kij",
          "parent_region_id":"-1",
          "cycles":"79058610",
          "real_time_nsec":"35204965",
          "PAPI_FP_OPS":"54000000",
          "PERF_COUNT_HW_CACHE_L1D:MISS":"45214817"
        },
        "6":{
          "name":"kji",
          "parent_region_id":"-1",
          "cycles":"27031770",
          "real_time_nsec":"12036974",
          "PAPI_FP_OPS":"54000000",
          "PERF_COUNT_HW_CACHE_L1D:MISS":"1783082"
        }
      }
    }
  }
}
