{
  "papi_version":"6.0.0.17",
  "cpu_info":"AMD EPYC 7742 64-Core Processor",
  "max_cpu_rate_mhz":"2250",
  "min_cpu_rate_mhz":"1500",
  "event_definitions":{
    "PAPI_FP_OPS":{
      "component":"perf_event",
      "type":"delta"
    },
    "PERF_COUNT_HW_CACHE_L1D:MISS":{
      "component":"perf_event",
      "type":"delta"
    }
  },
  "threads":{
    "0":{
      "regions":{
        "0":{
          "name":"initialize",
          "parent_region_id":"-1",
          "cycles":"1327432",
          "real_time_nsec":"589680",
          "PAPI_FP_OPS":"80000",
          "PERF_COUNT_HW_CACHE_L1D:MISS":"5371"
        },
        "1":{
          "name":"ijk",
          "parent_region_id":"-1",
          "cycles":"14838143",
          "real_time_nsec":"6607377",
          "PAPI_FP_OPS":"16000000",
          "PERF_COUNT_HW_CACHE_L1D:MISS":"533487"
        },
        "2":{
          "name":"ikj",
          "parent_region_id":"-1",
          "cycles":"5915722",
          "real_time_nsec":"2634160",
          "PAPI_FP_OPS":"16000000",
          "PERF_COUNT_HW_CACHE_L1D:MISS":"502696"
        },
        "3":{
          "name":"jik",
          "parent_region_id":"-1",
          "cycles":"14925285",
          "real_time_nsec":"6646132",
          "PAPI_FP_OPS":"16000000",
          "PERF_COUNT_HW_CACHE_L1D:MISS":"545462"
        },
        "4":{
          "name":"jki",
          "parent_region_id":"-1",
          "cycles":"9737820",
          "real_time_nsec":"4336212",
          "PAPI_FP_OPS":"16000000",
          "PERF_COUNT_HW_CACHE_L1D:MISS":"751491"
        },
        "5":{
          "name":"kij",
          "parent_region_id":"-1",
          "cycles":"11569208",
          "real_time_nsec":"5151997",
          "PAPI_FP_OPS":"16000000",
          "PERF_COUNT_HW_CACHE_L1D:MISS":"537980"
        },
        "6":{
          "name":"kji",
          "parent_region_id":"-1",
          "cycles":"10170878",
          "real_time_nsec":"4529242",
          "PAPI_FP_OPS":"16000000",
          "PERF_COUNT_HW_CACHE_L1D:MISS":"644227"
        }
      }
    }
  }
}
