{
  "papi_version":"6.0.0.17",
  "cpu_info":"AMD EPYC 7742 64-Core Processor",
  "max_cpu_rate_mhz":"2250",
  "min_cpu_rate_mhz":"1500",
  "event_definitions":{
    "PAPI_FP_OPS":{
      "component":"perf_event",
      "type":"delta"
    },
    "PERF_COUNT_HW_CACHE_L1D:MISS":{
      "component":"perf_event",
      "type":"delta"
    }
  },
  "threads":{
    "0":{
      "regions":{
        "0":{
          "name":"initialize",
          "parent_region_id":"-1",
          "cycles":"1624905",
          "real_time_nsec":"721253",
          "PAPI_FP_OPS":"80000",
          "PERF_COUNT_HW_CACHE_L1D:MISS":"5358"
        },
        "1":{
          "name":"ijk",
          "parent_region_id":"-1",
          "cycles":"14815665",
          "real_time_nsec":"6597467",
          "PAPI_FP_OPS":"16000000",
          "PERF_COUNT_HW_CACHE_L1D:MISS":"538895"
        },
        "2":{
          "name":"ikj",
          "parent_region_id":"-1",
          "cycles":"5990873",
          "real_time_nsec":"2668004",
          "PAPI_FP_OPS":"16000000",
          "PERF_COUNT_HW_CACHE_L1D:MISS":"757036"
        },
        "3":{
          "name":"jik",
          "parent_region_id":"-1",
          "cycles":"14767313",
          "real_time_nsec":"6575876",
          "PAPI_FP_OPS":"16000000",
          "PERF_COUNT_HW_CACHE_L1D:MISS":"527009"
        },
        "4":{
          "name":"jki",
          "parent_region_id":"-1",
          "cycles":"5820907",
          "real_time_nsec":"2592159",
          "PAPI_FP_OPS":"16000000",
          "PERF_COUNT_HW_CACHE_L1D:MISS":"503247"
        },
        "5":{
          "name":"kij",
          "parent_region_id":"-1",
          "cycles":"11427390",
          "real_time_nsec":"5088835",
          "PAPI_FP_OPS":"16000000",
          "PERF_COUNT_HW_CACHE_L1D:MISS":"625311"
        },
        "6":{
          "name":"kji",
          "parent_region_id":"-1",
          "cycles":"6987892",
          "real_time_nsec":"3111775",
          "PAPI_FP_OPS":"16000000",
          "PERF_COUNT_HW_CACHE_L1D:MISS":"539263"
        }
      }
    }
  }
}
