{
  "papi_version":"6.0.0.17",
  "cpu_info":"AMD EPYC 7742 64-Core Processor",
  "max_cpu_rate_mhz":"2250",
  "min_cpu_rate_mhz":"1500",
  "event_definitions":{
    "PAPI_FP_OPS":{
      "component":"perf_event",
      "type":"delta"
    },
    "PERF_COUNT_HW_CACHE_L1D:MISS":{
      "component":"perf_event",
      "type":"delta"
    }
  },
  "threads":{
    "0":{
      "regions":{
        "0":{
          "name":"initialize",
          "parent_region_id":"-1",
          "cycles":"33819412",
          "real_time_nsec":"15055871",
          "PAPI_FP_OPS":"980000",
          "PERF_COUNT_HW_CACHE_L1D:MISS":"62156"
        },
        "1":{
          "name":"ijk",
          "parent_region_id":"-1",
          "cycles":"834354698",
          "real_time_nsec":"371539624",
          "PAPI_FP_OPS":"686000000",
          "PERF_COUNT_HW_CACHE_L1D:MISS":"368925491"
        },
        "2":{
          "name":"ikj",
          "parent_region_id":"-1",
          "cycles":"649699020",
          "real_time_nsec":"289314557",
          "PAPI_FP_OPS":"686000000",
          "PERF_COUNT_HW_CACHE_L1D:MISS":"345333408"
        },
        "3":{
          "name":"jik",
          "parent_region_id":"-1",
          "cycles":"840516007",
          "real_time_nsec":"374281540",
          "PAPI_FP_OPS":"686000000",
          "PERF_COUNT_HW_CACHE_L1D:MISS":"368693851"
        },
        "4":{
          "name":"jki",
          "parent_region_id":"-1",
          "cycles":"318874117",
          "real_time_nsec":"141996342",
          "PAPI_FP_OPS":"686000000",
          "PERF_COUNT_HW_CACHE_L1D:MISS":"21784645"
        },
        "5":{
          "name":"kij",
          "parent_region_id":"-1",
          "cycles":"1234503495",
          "real_time_nsec":"549724045",
          "PAPI_FP_OPS":"686000000",
          "PERF_COUNT_HW_CACHE_L1D:MISS":"686550735"
        },
        "6":{
          "name":"kji",
          "parent_region_id":"-1",
          "cycles":"401254740",
          "real_time_nsec":"178680222",
          "PAPI_FP_OPS":"686000000",
          "PERF_COUNT_HW_CACHE_L1D:MISS":"22277050"
        }
      }
    }
  }
}
