{
  "papi_version":"6.0.0.17",
  "cpu_info":"AMD EPYC 7742 64-Core Processor",
  "max_cpu_rate_mhz":"2250",
  "min_cpu_rate_mhz":"1500",
  "event_definitions":{
    "PAPI_FP_OPS":{
      "component":"perf_event",
      "type":"delta"
    },
    "PERF_COUNT_HW_CACHE_L1D:MISS":{
      "component":"perf_event",
      "type":"delta"
    }
  },
  "threads":{
    "0":{
      "regions":{
        "0":{
          "name":"initialize",
          "parent_region_id":"-1",
          "cycles":"38125552",
          "real_time_nsec":"16972324",
          "PAPI_FP_OPS":"980000",
          "PERF_COUNT_HW_CACHE_L1D:MISS":"62562"
        },
        "1":{
          "name":"ijk",
          "parent_region_id":"-1",
          "cycles":"834047708",
          "real_time_nsec":"371400948",
          "PAPI_FP_OPS":"686000000",
          "PERF_COUNT_HW_CACHE_L1D:MISS":"368275987"
        },
        "2":{
          "name":"ikj",
          "parent_region_id":"-1",
          "cycles":"650655270",
          "real_time_nsec":"289735253",
          "PAPI_FP_OPS":"686000000",
          "PERF_COUNT_HW_CACHE_L1D:MISS":"345445826"
        },
        "3":{
          "name":"jik",
          "parent_region_id":"-1",
          "cycles":"840138367",
          "real_time_nsec":"374112335",
          "PAPI_FP_OPS":"686000000",
          "PERF_COUNT_HW_CACHE_L1D:MISS":"368379947"
        },
        "4":{
          "name":"jki",
          "parent_region_id":"-1",
          "cycles":"319125825",
          "real_time_nsec":"142106403",
          "PAPI_FP_OPS":"686000000",
          "PERF_COUNT_HW_CACHE_L1D:MISS":"21783597"
        },
        "5":{
          "name":"kij",
          "parent_region_id":"-1",
          "cycles":"1237915395",
          "real_time_nsec":"551241884",
          "PAPI_FP_OPS":"686000000",
          "PERF_COUNT_HW_CACHE_L1D:MISS":"686738776"
        },
        "6":{
          "name":"kji",
          "parent_region_id":"-1",
          "cycles":"399695850",
          "real_time_nsec":"177984198",
          "PAPI_FP_OPS":"686000000",
          "PERF_COUNT_HW_CACHE_L1D:MISS":"22275303"
        }
      }
    }
  }
}
