{
  "papi_version":"6.0.0.17",
  "cpu_info":"AMD EPYC 7742 64-Core Processor",
  "max_cpu_rate_mhz":"2250",
  "min_cpu_rate_mhz":"1500",
  "event_definitions":{
    "PAPI_FP_OPS":{
      "component":"perf_event",
      "type":"delta"
    },
    "PERF_COUNT_HW_CACHE_L1D:MISS":{
      "component":"perf_event",
      "type":"delta"
    }
  },
  "threads":{
    "0":{
      "regions":{
        "0":{
          "name":"initialize",
          "parent_region_id":"-1",
          "cycles":"133695",
          "real_time_nsec":"57220",
          "PAPI_FP_OPS":"7200",
          "PERF_COUNT_HW_CACHE_L1D:MISS":"645"
        },
        "1":{
          "name":"ijk",
          "parent_region_id":"-1",
          "cycles":"300397",
          "real_time_nsec":"133657",
          "PAPI_FP_OPS":"432000",
          "PERF_COUNT_HW_CACHE_L1D:MISS":"596"
        },
        "2":{
          "name":"ikj",
          "parent_region_id":"-1",
          "cycles":"229050",
          "real_time_nsec":"101946",
          "PAPI_FP_OPS":"432000",
          "PERF_COUNT_HW_CACHE_L1D:MISS":"528"
        },
        "3":{
          "name":"jik",
          "parent_region_id":"-1",
          "cycles":"326632",
          "real_time_nsec":"145388",
          "PAPI_FP_OPS":"432000",
          "PERF_COUNT_HW_CACHE_L1D:MISS":"4117"
        },
        "4":{
          "name":"jki",
          "parent_region_id":"-1",
          "cycles":"241605",
          "real_time_nsec":"107536",
          "PAPI_FP_OPS":"432000",
          "PERF_COUNT_HW_CACHE_L1D:MISS":"2247"
        },
        "5":{
          "name":"kij",
          "parent_region_id":"-1",
          "cycles":"315585",
          "real_time_nsec":"140500",
          "PAPI_FP_OPS":"432000",
          "PERF_COUNT_HW_CACHE_L1D:MISS":"895"
        },
        "6":{
          "name":"kji",
          "parent_region_id":"-1",
          "cycles":"507217",
          "real_time_nsec":"225692",
          "PAPI_FP_OPS":"432000",
          "PERF_COUNT_HW_CACHE_L1D:MISS":"881"
        }
      }
    }
  }
}
