{
  "papi_version":"6.0.0.17",
  "cpu_info":"AMD EPYC 7742 64-Core Processor",
  "max_cpu_rate_mhz":"2250",
  "min_cpu_rate_mhz":"1500",
  "event_definitions":{
    "PAPI_FP_OPS":{
      "component":"perf_event",
      "type":"delta"
    },
    "PERF_COUNT_HW_CACHE_L1D:MISS":{
      "component":"perf_event",
      "type":"delta"
    }
  },
  "threads":{
    "0":{
      "regions":{
        "0":{
          "name":"initialize",
          "parent_region_id":"-1",
          "cycles":"56403675",
          "real_time_nsec":"25114876",
          "PAPI_FP_OPS":"2000000",
          "PERF_COUNT_HW_CACHE_L1D:MISS":"131123"
        },
        "1":{
          "name":"ijk",
          "parent_region_id":"-1",
          "cycles":"3035826472",
          "real_time_nsec":"1351852280",
          "PAPI_FP_OPS":"2000000000",
          "PERF_COUNT_HW_CACHE_L1D:MISS":"1052558444"
        },
        "2":{
          "name":"ikj",
          "parent_region_id":"-1",
          "cycles":"935991720",
          "real_time_nsec":"416797385",
          "PAPI_FP_OPS":"2000000000",
          "PERF_COUNT_HW_CACHE_L1D:MISS":"63638980"
        },
        "3":{
          "name":"jik",
          "parent_region_id":"-1",
          "cycles":"2485002870",
          "real_time_nsec":"1106569529",
          "PAPI_FP_OPS":"2000000000",
          "PERF_COUNT_HW_CACHE_L1D:MISS":"1075944711"
        },
        "4":{
          "name":"jki",
          "parent_region_id":"-1",
          "cycles":"2315404215",
          "real_time_nsec":"1031049002",
          "PAPI_FP_OPS":"2000000000",
          "PERF_COUNT_HW_CACHE_L1D:MISS":"1005697346"
        },
        "5":{
          "name":"kij",
          "parent_region_id":"-1",
          "cycles":"1783972620",
          "real_time_nsec":"794403419",
          "PAPI_FP_OPS":"2000000000",
          "PERF_COUNT_HW_CACHE_L1D:MISS":"64478227"
        },
        "6":{
          "name":"kji",
          "parent_region_id":"-1",
          "cycles":"3946897125",
          "real_time_nsec":"1757546960",
          "PAPI_FP_OPS":"2000000000",
          "PERF_COUNT_HW_CACHE_L1D:MISS":"2001199033"
        }
      }
    }
  }
}
