{
  "papi_version":"6.0.0.17",
  "cpu_info":"AMD EPYC 7742 64-Core Processor",
  "max_cpu_rate_mhz":"2250",
  "min_cpu_rate_mhz":"1500",
  "event_definitions":{
    "PAPI_FP_OPS":{
      "component":"perf_event",
      "type":"delta"
    },
    "PERF_COUNT_HW_CACHE_L1D:MISS":{
      "component":"perf_event",
      "type":"delta"
    }
  },
  "threads":{
    "0":{
      "regions":{
        "0":{
          "name":"initialize",
          "parent_region_id":"-1",
          "cycles":"27038340",
          "real_time_nsec":"12037237",
          "PAPI_FP_OPS":"1620000",
          "PERF_COUNT_HW_CACHE_L1D:MISS":"102375"
        },
        "1":{
          "name":"ijk",
          "parent_region_id":"-1",
          "cycles":"1972375628",
          "real_time_nsec":"878297878",
          "PAPI_FP_OPS":"1458000000",
          "PERF_COUNT_HW_CACHE_L1D:MISS":"755895509"
        },
        "2":{
          "name":"ikj",
          "parent_region_id":"-1",
          "cycles":"733094235",
          "real_time_nsec":"326448331",
          "PAPI_FP_OPS":"1458000000",
          "PERF_COUNT_HW_CACHE_L1D:MISS":"46672360"
        },
        "3":{
          "name":"jik",
          "parent_region_id":"-1",
          "cycles":"1783018777",
          "real_time_nsec":"793975337",
          "PAPI_FP_OPS":"1458000000",
          "PERF_COUNT_HW_CACHE_L1D:MISS":"784100453"
        },
        "4":{
          "name":"jki",
          "parent_region_id":"-1",
          "cycles":"1358492625",
          "real_time_nsec":"604936088",
          "PAPI_FP_OPS":"1458000000",
          "PERF_COUNT_HW_CACHE_L1D:MISS":"733187089"
        },
        "5":{
          "name":"kij",
          "parent_region_id":"-1",
          "cycles":"1262393595",
          "real_time_nsec":"562141909",
          "PAPI_FP_OPS":"1458000000",
          "PERF_COUNT_HW_CACHE_L1D:MISS":"47085192"
        },
        "6":{
          "name":"kji",
          "parent_region_id":"-1",
          "cycles":"2711703825",
          "real_time_nsec":"1207518553",
          "PAPI_FP_OPS":"1458000000",
          "PERF_COUNT_HW_CACHE_L1D:MISS":"1458836971"
        }
      }
    }
  }
}
