{
  "papi_version":"6.0.0.17",
  "cpu_info":"AMD EPYC 7742 64-Core Processor",
  "max_cpu_rate_mhz":"2250",
  "min_cpu_rate_mhz":"1500",
  "event_definitions":{
    "PAPI_FP_OPS":{
      "component":"perf_event",
      "type":"delta"
    },
    "PERF_COUNT_HW_CACHE_L1D:MISS":{
      "component":"perf_event",
      "type":"delta"
    }
  },
  "threads":{
    "0":{
      "regions":{
        "0":{
          "name":"initialize",
          "parent_region_id":"-1",
          "cycles":"28308600",
          "real_time_nsec":"12604955",
          "PAPI_FP_OPS":"1620000",
          "PERF_COUNT_HW_CACHE_L1D:MISS":"102566"
        },
        "1":{
          "name":"ijk",
          "parent_region_id":"-1",
          "cycles":"1856322090",
          "real_time_nsec":"826619858",
          "PAPI_FP_OPS":"1458000000",
          "PERF_COUNT_HW_CACHE_L1D:MISS":"763727935"
        },
        "2":{
          "name":"ikj",
          "parent_region_id":"-1",
          "cycles":"752808938",
          "real_time_nsec":"335227120",
          "PAPI_FP_OPS":"1458000000",
          "PERF_COUNT_HW_CACHE_L1D:MISS":"46794475"
        },
        "3":{
          "name":"jik",
          "parent_region_id":"-1",
          "cycles":"1798671442",
          "real_time_nsec":"800946642",
          "PAPI_FP_OPS":"1458000000",
          "PERF_COUNT_HW_CACHE_L1D:MISS":"784560961"
        },
        "4":{
          "name":"jki",
          "parent_region_id":"-1",
          "cycles":"1382201505",
          "real_time_nsec":"615493878",
          "PAPI_FP_OPS":"1458000000",
          "PERF_COUNT_HW_CACHE_L1D:MISS":"733271941"
        },
        "5":{
          "name":"kij",
          "parent_region_id":"-1",
          "cycles":"1267844332",
          "real_time_nsec":"564571267",
          "PAPI_FP_OPS":"1458000000",
          "PERF_COUNT_HW_CACHE_L1D:MISS":"47096284"
        },
        "6":{
          "name":"kji",
          "parent_region_id":"-1",
          "cycles":"2680464960",
          "real_time_nsec":"1193608587",
          "PAPI_FP_OPS":"1458000000",
          "PERF_COUNT_HW_CACHE_L1D:MISS":"1458936261"
        }
      }
    }
  }
}
