{
  "papi_version":"6.0.0.17",
  "cpu_info":"AMD EPYC 7742 64-Core Processor",
  "max_cpu_rate_mhz":"2250",
  "min_cpu_rate_mhz":"1500",
  "event_definitions":{
    "PAPI_FP_OPS":{
      "component":"perf_event",
      "type":"delta"
    },
    "PERF_COUNT_HW_CACHE_L1D:MISS":{
      "component":"perf_event",
      "type":"delta"
    }
  },
  "threads":{
    "0":{
      "regions":{
        "0":{
          "name":"initialize",
          "parent_region_id":"-1",
          "cycles":"19309230",
          "real_time_nsec":"8597301",
          "PAPI_FP_OPS":"980000",
          "PERF_COUNT_HW_CACHE_L1D:MISS":"63164"
        },
        "1":{
          "name":"ijk",
          "parent_region_id":"-1",
          "cycles":"897649268",
          "real_time_nsec":"399723193",
          "PAPI_FP_OPS":"686000000",
          "PERF_COUNT_HW_CACHE_L1D:MISS":"355807216"
        },
        "2":{
          "name":"ikj",
          "parent_region_id":"-1",
          "cycles":"387202185",
          "real_time_nsec":"172422344",
          "PAPI_FP_OPS":"686000000",
          "PERF_COUNT_HW_CACHE_L1D:MISS":"21975906"
        },
        "3":{
          "name":"jik",
          "parent_region_id":"-1",
          "cycles":"851147100",
          "real_time_nsec":"379015615",
          "PAPI_FP_OPS":"686000000",
          "PERF_COUNT_HW_CACHE_L1D:MISS":"368951060"
        },
        "4":{
          "name":"jki",
          "parent_region_id":"-1",
          "cycles":"623463142",
          "real_time_nsec":"277629062",
          "PAPI_FP_OPS":"686000000",
          "PERF_COUNT_HW_CACHE_L1D:MISS":"345339395"
        },
        "5":{
          "name":"kij",
          "parent_region_id":"-1",
          "cycles":"596831378",
          "real_time_nsec":"265769035",
          "PAPI_FP_OPS":"686000000",
          "PERF_COUNT_HW_CACHE_L1D:MISS":"22185251"
        },
        "6":{
          "name":"kji",
          "parent_region_id":"-1",
          "cycles":"1151495348",
          "real_time_nsec":"512758448",
          "PAPI_FP_OPS":"686000000",
          "PERF_COUNT_HW_CACHE_L1D:MISS":"686520078"
        }
      }
    }
  }
}
