{
  "papi_version":"6.0.0.17",
  "cpu_info":"AMD EPYC 7742 64-Core Processor",
  "max_cpu_rate_mhz":"2250",
  "min_cpu_rate_mhz":"1500",
  "event_definitions":{
    "PAPI_FP_OPS":{
      "component":"perf_event",
      "type":"delta"
    },
    "PERF_COUNT_HW_CACHE_L1D:MISS":{
      "component":"perf_event",
      "type":"delta"
    }
  },
  "threads":{
    "0":{
      "regions":{
        "0":{
          "name":"initialize",
          "parent_region_id":"-1",
          "cycles":"29278890",
          "real_time_nsec":"13036862",
          "PAPI_FP_OPS":"980000",
          "PERF_COUNT_HW_CACHE_L1D:MISS":"62835"
        },
        "1":{
          "name":"ijk",
          "parent_region_id":"-1",
          "cycles":"783810247",
          "real_time_nsec":"349030573",
          "PAPI_FP_OPS":"686000000",
          "PERF_COUNT_HW_CACHE_L1D:MISS":"360169391"
        },
        "2":{
          "name":"ikj",
          "parent_region_id":"-1",
          "cycles":"587802307",
          "real_time_nsec":"261746945",
          "PAPI_FP_OPS":"686000000",
          "PERF_COUNT_HW_CACHE_L1D:MISS":"22003963"
        },
        "3":{
          "name":"jik",
          "parent_region_id":"-1",
          "cycles":"860545260",
          "real_time_nsec":"383199335",
          "PAPI_FP_OPS":"686000000",
          "PERF_COUNT_HW_CACHE_L1D:MISS":"359928531"
        },
        "4":{
          "name":"jki",
          "parent_region_id":"-1",
          "cycles":"618184238",
          "real_time_nsec":"275276010",
          "PAPI_FP_OPS":"686000000",
          "PERF_COUNT_HW_CACHE_L1D:MISS":"345548405"
        },
        "5":{
          "name":"kij",
          "parent_region_id":"-1",
          "cycles":"607987867",
          "real_time_nsec":"270736458",
          "PAPI_FP_OPS":"686000000",
          "PERF_COUNT_HW_CACHE_L1D:MISS":"22189986"
        },
        "6":{
          "name":"kji",
          "parent_region_id":"-1",
          "cycles":"1194672397",
          "real_time_nsec":"531985307",
          "PAPI_FP_OPS":"686000000",
          "PERF_COUNT_HW_CACHE_L1D:MISS":"686519957"
        }
      }
    }
  }
}
