{
  "papi_version":"6.0.0.17",
  "cpu_info":"AMD EPYC 7742 64-Core Processor",
  "max_cpu_rate_mhz":"2250",
  "min_cpu_rate_mhz":"1500",
  "event_definitions":{
    "PAPI_FP_OPS":{
      "component":"perf_event",
      "type":"delta"
    },
    "PERF_COUNT_HW_CACHE_L1D:MISS":{
      "component":"perf_event",
      "type":"delta"
    }
  },
  "threads":{
    "0":{
      "regions":{
        "0":{
          "name":"initialize",
          "parent_region_id":"-1",
          "cycles":"18663885",
          "real_time_nsec":"8308668",
          "PAPI_FP_OPS":"980000",
          "PERF_COUNT_HW_CACHE_L1D:MISS":"62438"
        },
        "1":{
          "name":"ijk",
          "parent_region_id":"-1",
          "cycles":"956366820",
          "real_time_nsec":"425871842",
          "PAPI_FP_OPS":"686000000",
          "PERF_COUNT_HW_CACHE_L1D:MISS":"359160792"
        },
        "2":{
          "name":"ikj",
          "parent_region_id":"-1",
          "cycles":"400320225",
          "real_time_nsec":"178263021",
          "PAPI_FP_OPS":"686000000",
          "PERF_COUNT_HW_CACHE_L1D:MISS":"22026905"
        },
        "3":{
          "name":"jik",
          "parent_region_id":"-1",
          "cycles":"843658830",
          "real_time_nsec":"375683006",
          "PAPI_FP_OPS":"686000000",
          "PERF_COUNT_HW_CACHE_L1D:MISS":"368401349"
        },
        "4":{
          "name":"jki",
          "parent_region_id":"-1",
          "cycles":"627809468",
          "real_time_nsec":"279564792",
          "PAPI_FP_OPS":"686000000",
          "PERF_COUNT_HW_CACHE_L1D:MISS":"345612601"
        },
        "5":{
          "name":"kij",
          "parent_region_id":"-1",
          "cycles":"591338452",
          "real_time_nsec":"263322455",
          "PAPI_FP_OPS":"686000000",
          "PERF_COUNT_HW_CACHE_L1D:MISS":"22198846"
        },
        "6":{
          "name":"kji",
          "parent_region_id":"-1",
          "cycles":"1167822922",
          "real_time_nsec":"520029948",
          "PAPI_FP_OPS":"686000000",
          "PERF_COUNT_HW_CACHE_L1D:MISS":"686523559"
        }
      }
    }
  }
}
