{
  "papi_version":"6.0.0.17",
  "cpu_info":"AMD EPYC 7742 64-Core Processor",
  "max_cpu_rate_mhz":"2250",
  "min_cpu_rate_mhz":"1500",
  "event_definitions":{
    "PAPI_FP_OPS":{
      "component":"perf_event",
      "type":"delta"
    },
    "PERF_COUNT_HW_CACHE_L1D:MISS":{
      "component":"perf_event",
      "type":"delta"
    }
  },
  "threads":{
    "0":{
      "regions":{
        "0":{
          "name":"initialize",
          "parent_region_id":"-1",
          "cycles":"33157800",
          "real_time_nsec":"14764752",
          "PAPI_FP_OPS":"1620000",
          "PERF_COUNT_HW_CACHE_L1D:MISS":"104516"
        },
        "1":{
          "name":"ijk",
          "parent_region_id":"-1",
          "cycles":"1850061645",
          "real_time_nsec":"823832504",
          "PAPI_FP_OPS":"1458000000",
          "PERF_COUNT_HW_CACHE_L1D:MISS":"768123708"
        },
        "2":{
          "name":"ikj",
          "parent_region_id":"-1",
          "cycles":"1375696575",
          "real_time_nsec":"612597438",
          "PAPI_FP_OPS":"1458000000",
          "PERF_COUNT_HW_CACHE_L1D:MISS":"733082431"
        },
        "3":{
          "name":"jik",
          "parent_region_id":"-1",
          "cycles":"1820202165",
          "real_time_nsec":"810532959",
          "PAPI_FP_OPS":"1458000000",
          "PERF_COUNT_HW_CACHE_L1D:MISS":"785019955"
        },
        "4":{
          "name":"jki",
          "parent_region_id":"-1",
          "cycles":"661018590",
          "real_time_nsec":"294352534",
          "PAPI_FP_OPS":"1458000000",
          "PERF_COUNT_HW_CACHE_L1D:MISS":"46543576"
        },
        "5":{
          "name":"kij",
          "parent_region_id":"-1",
          "cycles":"2696574308",
          "real_time_nsec":"1200780174",
          "PAPI_FP_OPS":"1458000000",
          "PERF_COUNT_HW_CACHE_L1D:MISS":"1458642121"
        },
        "6":{
          "name":"kji",
          "parent_region_id":"-1",
          "cycles":"845101440",
          "real_time_nsec":"376322933",
          "PAPI_FP_OPS":"1458000000",
          "PERF_COUNT_HW_CACHE_L1D:MISS":"47249103"
        }
      }
    }
  }
}
