{
  "papi_version":"6.0.0.17",
  "cpu_info":"AMD EPYC 7742 64-Core Processor",
  "max_cpu_rate_mhz":"2250",
  "min_cpu_rate_mhz":"1500",
  "event_definitions":{
    "PAPI_FP_OPS":{
      "component":"perf_event",
      "type":"delta"
    },
    "PERF_COUNT_HW_CACHE_L1D:MISS":{
      "component":"perf_event",
      "type":"delta"
    }
  },
  "threads":{
    "0":{
      "regions":{
        "0":{
          "name":"initialize",
          "parent_region_id":"-1",
          "cycles":"47847825",
          "real_time_nsec":"21304839",
          "PAPI_FP_OPS":"1620000",
          "PERF_COUNT_HW_CACHE_L1D:MISS":"103020"
        },
        "1":{
          "name":"ijk",
          "parent_region_id":"-1",
          "cycles":"1788318247",
          "real_time_nsec":"796337699",
          "PAPI_FP_OPS":"1458000000",
          "PERF_COUNT_HW_CACHE_L1D:MISS":"764099401"
        },
        "2":{
          "name":"ikj",
          "parent_region_id":"-1",
          "cycles":"1402052625",
          "real_time_nsec":"624332412",
          "PAPI_FP_OPS":"1458000000",
          "PERF_COUNT_HW_CACHE_L1D:MISS":"733124671"
        },
        "3":{
          "name":"jik",
          "parent_region_id":"-1",
          "cycles":"1814929785",
          "real_time_nsec":"808185951",
          "PAPI_FP_OPS":"1458000000",
          "PERF_COUNT_HW_CACHE_L1D:MISS":"785111783"
        },
        "4":{
          "name":"jki",
          "parent_region_id":"-1",
          "cycles":"657857138",
          "real_time_nsec":"292942421",
          "PAPI_FP_OPS":"1458000000",
          "PERF_COUNT_HW_CACHE_L1D:MISS":"46589033"
        },
        "5":{
          "name":"kij",
          "parent_region_id":"-1",
          "cycles":"2721539610",
          "real_time_nsec":"1211898928",
          "PAPI_FP_OPS":"1458000000",
          "PERF_COUNT_HW_CACHE_L1D:MISS":"1459111737"
        },
        "6":{
          "name":"kji",
          "parent_region_id":"-1",
          "cycles":"834714720",
          "real_time_nsec":"371697807",
          "PAPI_FP_OPS":"1458000000",
          "PERF_COUNT_HW_CACHE_L1D:MISS":"47190724"
        }
      }
    }
  }
}
