{
  "papi_version":"6.0.0.17",
  "cpu_info":"AMD EPYC 7742 64-Core Processor",
  "max_cpu_rate_mhz":"2250",
  "min_cpu_rate_mhz":"1500",
  "event_definitions":{
    "PAPI_FP_OPS":{
      "component":"perf_event",
      "type":"delta"
    },
    "PERF_COUNT_HW_CACHE_L1D:MISS":{
      "component":"perf_event",
      "type":"delta"
    }
  },
  "threads":{
    "0":{
      "regions":{
        "0":{
          "name":"initialize",
          "parent_region_id":"-1",
          "cycles":"31833382",
          "real_time_nsec":"14175173",
          "PAPI_FP_OPS":"1620000",
          "PERF_COUNT_HW_CACHE_L1D:MISS":"102851"
        },
        "1":{
          "name":"ijk",
          "parent_region_id":"-1",
          "cycles":"1890829845",
          "real_time_nsec":"841985320",
          "PAPI_FP_OPS":"1458000000",
          "PERF_COUNT_HW_CACHE_L1D:MISS":"763162407"
        },
        "2":{
          "name":"ikj",
          "parent_region_id":"-1",
          "cycles":"1480200885",
          "real_time_nsec":"659131929",
          "PAPI_FP_OPS":"1458000000",
          "PERF_COUNT_HW_CACHE_L1D:MISS":"733189183"
        },
        "3":{
          "name":"jik",
          "parent_region_id":"-1",
          "cycles":"1800624353",
          "real_time_nsec":"801815860",
          "PAPI_FP_OPS":"1458000000",
          "PERF_COUNT_HW_CACHE_L1D:MISS":"785119424"
        },
        "4":{
          "name":"jki",
          "parent_region_id":"-1",
          "cycles":"674166398",
          "real_time_nsec":"300208480",
          "PAPI_FP_OPS":"1458000000",
          "PERF_COUNT_HW_CACHE_L1D:MISS":"46556834"
        },
        "5":{
          "name":"kij",
          "parent_region_id":"-1",
          "cycles":"2675175728",
          "real_time_nsec":"1191252520",
          "PAPI_FP_OPS":"1458000000",
          "PERF_COUNT_HW_CACHE_L1D:MISS":"1458732202"
        },
        "6":{
          "name":"kji",
          "parent_region_id":"-1",
          "cycles":"831763552",
          "real_time_nsec":"370383618",
          "PAPI_FP_OPS":"1458000000",
          "PERF_COUNT_HW_CACHE_L1D:MISS":"47247590"
        }
      }
    }
  }
}
