{
  "papi_version":"6.0.0.17",
  "cpu_info":"AMD EPYC 7742 64-Core Processor",
  "max_cpu_rate_mhz":"2250",
  "min_cpu_rate_mhz":"1500",
  "event_definitions":{
    "PAPI_FP_OPS":{
      "component":"perf_event",
      "type":"delta"
    },
    "PERF_COUNT_HW_CACHE_L1D:MISS":{
      "component":"perf_event",
      "type":"delta"
    }
  },
  "threads":{
    "0":{
      "regions":{
        "0":{
          "name":"initialize",
          "parent_region_id":"-1",
          "cycles":"46861267",
          "real_time_nsec":"20866790",
          "PAPI_FP_OPS":"1620000",
          "PERF_COUNT_HW_CACHE_L1D:MISS":"102472"
        },
        "1":{
          "name":"ijk",
          "parent_region_id":"-1",
          "cycles":"1790110080",
          "real_time_nsec":"797134255",
          "PAPI_FP_OPS":"1458000000",
          "PERF_COUNT_HW_CACHE_L1D:MISS":"772693189"
        },
        "2":{
          "name":"ikj",
          "parent_region_id":"-1",
          "cycles":"1602783585",
          "real_time_nsec":"713717384",
          "PAPI_FP_OPS":"1458000000",
          "PERF_COUNT_HW_CACHE_L1D:MISS":"733477518"
        },
        "3":{
          "name":"jik",
          "parent_region_id":"-1",
          "cycles":"1913291257",
          "real_time_nsec":"851986582",
          "PAPI_FP_OPS":"1458000000",
          "PERF_COUNT_HW_CACHE_L1D:MISS":"785289672"
        },
        "4":{
          "name":"jki",
          "parent_region_id":"-1",
          "cycles":"681663578",
          "real_time_nsec":"303546989",
          "PAPI_FP_OPS":"1458000000",
          "PERF_COUNT_HW_CACHE_L1D:MISS":"46522205"
        },
        "5":{
          "name":"kij",
          "parent_region_id":"-1",
          "cycles":"2670318022",
          "real_time_nsec":"1189090235",
          "PAPI_FP_OPS":"1458000000",
          "PERF_COUNT_HW_CACHE_L1D:MISS":"1459180850"
        },
        "6":{
          "name":"kji",
          "parent_region_id":"-1",
          "cycles":"806026410",
          "real_time_nsec":"358922608",
          "PAPI_FP_OPS":"1458000000",
          "PERF_COUNT_HW_CACHE_L1D:MISS":"47213710"
        }
      }
    }
  }
}
