{
  "papi_version":"6.0.0.17",
  "cpu_info":"AMD EPYC 7742 64-Core Processor",
  "max_cpu_rate_mhz":"2250",
  "min_cpu_rate_mhz":"1500",
  "event_definitions":{
    "PAPI_FP_OPS":{
      "component":"perf_event",
      "type":"delta"
    },
    "PERF_COUNT_HW_CACHE_L1D:MISS":{
      "component":"perf_event",
      "type":"delta"
    }
  },
  "threads":{
    "0":{
      "regions":{
        "0":{
          "name":"initialize",
          "parent_region_id":"-1",
          "cycles":"38152417",
          "real_time_nsec":"16991762",
          "PAPI_FP_OPS":"2000000",
          "PERF_COUNT_HW_CACHE_L1D:MISS":"126334"
        },
        "1":{
          "name":"ijk",
          "parent_region_id":"-1",
          "cycles":"2457053100",
          "real_time_nsec":"1094123875",
          "PAPI_FP_OPS":"2000000000",
          "PERF_COUNT_HW_CACHE_L1D:MISS":"1071256848"
        },
        "2":{
          "name":"ikj",
          "parent_region_id":"-1",
          "cycles":"2277833963",
          "real_time_nsec":"1014316191",
          "PAPI_FP_OPS":"2000000000",
          "PERF_COUNT_HW_CACHE_L1D:MISS":"1005746843"
        },
        "3":{
          "name":"jik",
          "parent_region_id":"-1",
          "cycles":"2693384865",
          "real_time_nsec":"1199360202",
          "PAPI_FP_OPS":"2000000000",
          "PERF_COUNT_HW_CACHE_L1D:MISS":"1072005597"
        },
        "4":{
          "name":"jki",
          "parent_region_id":"-1",
          "cycles":"974612362",
          "real_time_nsec":"433997761",
          "PAPI_FP_OPS":"2000000000",
          "PERF_COUNT_HW_CACHE_L1D:MISS":"63634556"
        },
        "5":{
          "name":"kij",
          "parent_region_id":"-1",
          "cycles":"4054401067",
          "real_time_nsec":"1805418965",
          "PAPI_FP_OPS":"2000000000",
          "PERF_COUNT_HW_CACHE_L1D:MISS":"2001647697"
        },
        "6":{
          "name":"kji",
          "parent_region_id":"-1",
          "cycles":"1233401265",
          "real_time_nsec":"549230740",
          "PAPI_FP_OPS":"2000000000",
          "PERF_COUNT_HW_CACHE_L1D:MISS":"64615026"
        }
      }
    }
  }
}
