{
  "papi_version":"6.0.0.17",
  "cpu_info":"AMD EPYC 7742 64-Core Processor",
  "max_cpu_rate_mhz":"2250",
  "min_cpu_rate_mhz":"1500",
  "event_definitions":{
    "PAPI_FP_OPS":{
      "component":"perf_event",
      "type":"delta"
    },
    "PERF_COUNT_HW_CACHE_L1D:MISS":{
      "component":"perf_event",
      "type":"delta"
    }
  },
  "threads":{
    "0":{
      "regions":{
        "0":{
          "name":"initialize",
          "parent_region_id":"-1",
          "cycles":"351697",
          "real_time_nsec":"152884",
          "PAPI_FP_OPS":"20000",
          "PERF_COUNT_HW_CACHE_L1D:MISS":"1410"
        },
        "1":{
          "name":"ijk",
          "parent_region_id":"-1",
          "cycles":"1670445",
          "real_time_nsec":"743917",
          "PAPI_FP_OPS":"2000000",
          "PERF_COUNT_HW_CACHE_L1D:MISS":"57575"
        },
        "2":{
          "name":"ikj",
          "parent_region_id":"-1",
          "cycles":"915098",
          "real_time_nsec":"407240",
          "PAPI_FP_OPS":"2000000",
          "PERF_COUNT_HW_CACHE_L1D:MISS":"62379"
        },
        "3":{
          "name":"jik",
          "parent_region_id":"-1",
          "cycles":"1662570",
          "real_time_nsec":"740440",
          "PAPI_FP_OPS":"2000000",
          "PERF_COUNT_HW_CACHE_L1D:MISS":"64738"
        },
        "4":{
          "name":"jki",
          "parent_region_id":"-1",
          "cycles":"787320",
          "real_time_nsec":"350743",
          "PAPI_FP_OPS":"2000000",
          "PERF_COUNT_HW_CACHE_L1D:MISS":"69675"
        },
        "5":{
          "name":"kij",
          "parent_region_id":"-1",
          "cycles":"1541520",
          "real_time_nsec":"686587",
          "PAPI_FP_OPS":"2000000",
          "PERF_COUNT_HW_CACHE_L1D:MISS":"72570"
        },
        "6":{
          "name":"kji",
          "parent_region_id":"-1",
          "cycles":"1101465",
          "real_time_nsec":"490500",
          "PAPI_FP_OPS":"2000000",
          "PERF_COUNT_HW_CACHE_L1D:MISS":"58704"
        }
      }
    }
  }
}
