{
  "papi_version":"6.0.0.17",
  "cpu_info":"AMD EPYC 7742 64-Core Processor",
  "max_cpu_rate_mhz":"2250",
  "min_cpu_rate_mhz":"1500",
  "event_definitions":{
    "PAPI_FP_OPS":{
      "component":"perf_event",
      "type":"delta"
    },
    "PERF_COUNT_HW_CACHE_L1D:MISS":{
      "component":"perf_event",
      "type":"delta"
    }
  },
  "threads":{
    "0":{
      "regions":{
        "0":{
          "name":"initialize",
          "parent_region_id":"-1",
          "cycles":"18443272",
          "real_time_nsec":"8209427",
          "PAPI_FP_OPS":"720000",
          "PERF_COUNT_HW_CACHE_L1D:MISS":"46747"
        },
        "1":{
          "name":"ijk",
          "parent_region_id":"-1",
          "cycles":"437029358",
          "real_time_nsec":"194608627",
          "PAPI_FP_OPS":"432000000",
          "PERF_COUNT_HW_CACHE_L1D:MISS":"221100192"
        },
        "2":{
          "name":"ikj",
          "parent_region_id":"-1",
          "cycles":"189678825",
          "real_time_nsec":"84464563",
          "PAPI_FP_OPS":"432000000",
          "PERF_COUNT_HW_CACHE_L1D:MISS":"13701679"
        },
        "3":{
          "name":"jik",
          "parent_region_id":"-1",
          "cycles":"600870622",
          "real_time_nsec":"267567914",
          "PAPI_FP_OPS":"432000000",
          "PERF_COUNT_HW_CACHE_L1D:MISS":"209605547"
        },
        "4":{
          "name":"jki",
          "parent_region_id":"-1",
          "cycles":"406326803",
          "real_time_nsec":"180938389",
          "PAPI_FP_OPS":"432000000",
          "PERF_COUNT_HW_CACHE_L1D:MISS":"206468810"
        },
        "5":{
          "name":"kij",
          "parent_region_id":"-1",
          "cycles":"492822225",
          "real_time_nsec":"219453154",
          "PAPI_FP_OPS":"432000000",
          "PERF_COUNT_HW_CACHE_L1D:MISS":"14104273"
        },
        "6":{
          "name":"kji",
          "parent_region_id":"-1",
          "cycles":"767485778",
          "real_time_nsec":"341759653",
          "PAPI_FP_OPS":"432000000",
          "PERF_COUNT_HW_CACHE_L1D:MISS":"424444886"
        }
      }
    }
  }
}
