{
  "papi_version":"6.0.0.17",
  "cpu_info":"AMD EPYC 7742 64-Core Processor",
  "max_cpu_rate_mhz":"2250",
  "min_cpu_rate_mhz":"1500",
  "event_definitions":{
    "PAPI_FP_OPS":{
      "component":"perf_event",
      "type":"delta"
    },
    "PERF_COUNT_HW_CACHE_L1D:MISS":{
      "component":"perf_event",
      "type":"delta"
    }
  },
  "threads":{
    "0":{
      "regions":{
        "0":{
          "name":"initialize",
          "parent_region_id":"-1",
          "cycles":"13653990",
          "real_time_nsec":"6078843",
          "PAPI_FP_OPS":"720000",
          "PERF_COUNT_HW_CACHE_L1D:MISS":"45429"
        },
        "1":{
          "name":"ijk",
          "parent_region_id":"-1",
          "cycles":"543847455",
          "real_time_nsec":"242176677",
          "PAPI_FP_OPS":"432000000",
          "PERF_COUNT_HW_CACHE_L1D:MISS":"221384609"
        },
        "2":{
          "name":"ikj",
          "parent_region_id":"-1",
          "cycles":"253653008",
          "real_time_nsec":"112951675",
          "PAPI_FP_OPS":"432000000",
          "PERF_COUNT_HW_CACHE_L1D:MISS":"13747511"
        },
        "3":{
          "name":"jik",
          "parent_region_id":"-1",
          "cycles":"550622700",
          "real_time_nsec":"245192980",
          "PAPI_FP_OPS":"432000000",
          "PERF_COUNT_HW_CACHE_L1D:MISS":"199495911"
        },
        "4":{
          "name":"jki",
          "parent_region_id":"-1",
          "cycles":"415390860",
          "real_time_nsec":"184973445",
          "PAPI_FP_OPS":"432000000",
          "PERF_COUNT_HW_CACHE_L1D:MISS":"206257196"
        },
        "5":{
          "name":"kij",
          "parent_region_id":"-1",
          "cycles":"459173970",
          "real_time_nsec":"204469409",
          "PAPI_FP_OPS":"432000000",
          "PERF_COUNT_HW_CACHE_L1D:MISS":"14097778"
        },
        "6":{
          "name":"kji",
          "parent_region_id":"-1",
          "cycles":"720885488",
          "real_time_nsec":"321008923",
          "PAPI_FP_OPS":"432000000",
          "PERF_COUNT_HW_CACHE_L1D:MISS":"432380552"
        }
      }
    }
  }
}
